typed_urdf/__init__.py
typed_urdf/robot.py
typed_urdf/components/__init__.py
typed_urdf/components/_utils.py
typed_urdf/components/base.py
typed_urdf/components/extra.py
typed_urdf/components/geometry.py
typed_urdf/components/joint.py
typed_urdf/components/link.py
typed_urdf/components/transmission.py
typed_urdf-0.1.2.dist-info/METADATA
typed_urdf-0.1.2.dist-info/WHEEL
typed_urdf-0.1.2.dist-info/top_level.txt
typed_urdf-0.1.2.dist-info/RECORD
